{
	"services": [
		{
		  "id": "apollo-configservice-2",
		  "name": "apollo-configservice",
		  "address": "192.168.0.102",
		  "port": 8080,
		  "check": {
			"deregisterCriticalServiceAfter": "90m",
			"http": "http://192.168.0.102:8080/health",
			"interval": "10s"
		  }
		},
		{
		  "id": "apollo-adminservice-2",
		  "name": "apollo-adminservice",
		  "address": "192.168.0.102",
		  "port": 8090,
		  "check": {
			"deregisterCriticalServiceAfter": "90m",
			"http": "http://192.168.0.102:8090/health",
			"interval": "10s"
		  }
		},
		{
		  "id": "apollo-portal-2",
		  "name": "apollo-portal",
		  "address": "192.168.0.102",
		  "port": 8070,
		  "check": {
			"deregisterCriticalServiceAfter": "90m",
			"http": "http://192.168.0.102:8070/health",
			"interval": "10s"
		  }
		}
	]
}